deepcon/__init__.py
deepcon/deepcon-covariance.py
deepconpkg-0.0.3.dist-info/LICENSE.txt
deepconpkg-0.0.3.dist-info/METADATA
deepconpkg-0.0.3.dist-info/WHEEL
deepconpkg-0.0.3.dist-info/top_level.txt
deepconpkg-0.0.3.dist-info/RECORD
