Metadata-Version: 2.1
Name: deepconpkg
Version: 0.0.3
Summary: Protein Contact Prediction using Dilated Convolutional Neural Networks with Dropout
Home-page: https://github.com/Chaserich1/deepconpkg
Author: Badri Adhikari
Author-email: adhikarib@umsl.edu
License: UNKNOWN
Platform: UNKNOWN
Classifier: Programming Language :: Python
Classifier: License :: OSI Approved :: MIT License
Classifier: Intended Audience :: Science/Research
Classifier: Operating System :: OS Independent
Requires-Dist: numpy
Requires-Dist: pyYAML
Requires-Dist: tensorflow
Requires-Dist: keras
